MANIFEST.in
README.rst
setup.py
aliyun_python_sdk_linkedmall.egg-info/PKG-INFO
aliyun_python_sdk_linkedmall.egg-info/SOURCES.txt
aliyun_python_sdk_linkedmall.egg-info/dependency_links.txt
aliyun_python_sdk_linkedmall.egg-info/requires.txt
aliyun_python_sdk_linkedmall.egg-info/top_level.txt
aliyunsdklinkedmall/__init__.py
aliyunsdklinkedmall/endpoint.py
aliyunsdklinkedmall/request/__init__.py
aliyunsdklinkedmall/request/v20180116/AddAddressRequest.py
aliyunsdklinkedmall/request/v20180116/AddItemLimitRuleRequest.py
aliyunsdklinkedmall/request/v20180116/AddSupplierNewItemsRequest.py
aliyunsdklinkedmall/request/v20180116/ApplyRefundRequest.py
aliyunsdklinkedmall/request/v20180116/BatchRegistAnonymousTbAccountRequest.py
aliyunsdklinkedmall/request/v20180116/CancelOrderRequest.py
aliyunsdklinkedmall/request/v20180116/CancelRefundRequest.py
aliyunsdklinkedmall/request/v20180116/ConfirmDisburseRequest.py
aliyunsdklinkedmall/request/v20180116/CreateMovieTicketOrderRequest.py
aliyunsdklinkedmall/request/v20180116/CreateOrderRequest.py
aliyunsdklinkedmall/request/v20180116/CreateOrderV2Request.py
aliyunsdklinkedmall/request/v20180116/CreatePayUrlRequest.py
aliyunsdklinkedmall/request/v20180116/CreateVirtualProductOrderRequest.py
aliyunsdklinkedmall/request/v20180116/DeleteBizItemsRequest.py
aliyunsdklinkedmall/request/v20180116/DeleteItemLimitRuleRequest.py
aliyunsdklinkedmall/request/v20180116/EnableOrderRequest.py
aliyunsdklinkedmall/request/v20180116/GetCategoryChainRequest.py
aliyunsdklinkedmall/request/v20180116/GetCategoryListRequest.py
aliyunsdklinkedmall/request/v20180116/GetCustomServiceUrlRequest.py
aliyunsdklinkedmall/request/v20180116/GetGuidePageRequest.py
aliyunsdklinkedmall/request/v20180116/GetLoginPageRequest.py
aliyunsdklinkedmall/request/v20180116/GetSwitchUrlRequest.py
aliyunsdklinkedmall/request/v20180116/GetUserInfoRequest.py
aliyunsdklinkedmall/request/v20180116/InitApplyRefundRequest.py
aliyunsdklinkedmall/request/v20180116/ListItemActivitiesRequest.py
aliyunsdklinkedmall/request/v20180116/ModifyBasicAndBizItemsRequest.py
aliyunsdklinkedmall/request/v20180116/ModifyBizItemsRequest.py
aliyunsdklinkedmall/request/v20180116/ModifyItemLimitRuleRequest.py
